netopsauto/__init__.py
netopsauto/juniper.py
netopsauto-0.1.dist-info/LICENSE
netopsauto-0.1.dist-info/METADATA
netopsauto-0.1.dist-info/WHEEL
netopsauto-0.1.dist-info/top_level.txt
netopsauto-0.1.dist-info/RECORD
