Metadata-Version: 2.1
Name: netopsauto
Version: 0.1
Summary: Useful tools to automate your network
Home-page: https://github.com/dmtx97/netopsauto
Author: Daniel Mendez
Author-email: dmtx97@gmail.com
License: UNKNOWN
Platform: UNKNOWN
Requires-Dist: junos-eznc (>=2.5.4)
Requires-Dist: bcrypt (>=3.2.0)
Requires-Dist: cryptography (>=3.2.1)
Requires-Dist: textfsm (>=0.3.2)
